{
  "id": "11",
  "subject": "Implement valid review suggestions",
  "description": "**Type:** Task\n\nReview findings from product review, CodeRabbit, local code review, and technical review. Implement valid suggestions. Skip suggestions conflicting with plan architecture decisions.\n\n**Verification:** `bun run test -- tests/unit/utils/fibonacci.test.ts && bun run lint -- src/utils/fibonacci.ts tests/unit/utils/fibonacci.test.ts && bun run typecheck` → All pass",
  "activeForm": "Implementing review suggestions",
  "owner": "team-lead",
  "status": "completed",
  "blocks": [
    "12"
  ],
  "blockedBy": [
    "7",
    "8",
    "9",
    "10"
  ],
  "metadata": {
    "plan": "fibonacci-generator",
    "type": "task"
  }
}